README.md
setup.cfg
setup.py
pymidi/__init__.py
pymidi/packets.py
pymidi/protocol.py
pymidi/server.py
pymidi/utils.py
pymidi.egg-info/PKG-INFO
pymidi.egg-info/SOURCES.txt
pymidi.egg-info/dependency_links.txt
pymidi.egg-info/requires.txt
pymidi.egg-info/top_level.txt
pymidi/tests/__init__.py
pymidi/tests/packets_test.py
pymidi/tests/server_tests.py
pymidi/tests/utils_test.py