Metadata-Version: 2.1
Name: pymidi
Version: 0.4.0
Summary: Python RTP-MIDI / AppleMIDI driver
Home-page: https://github.com/mik3y/pymidi
Author: mike wakerly
Author-email: opensource@hoho.com
License: MIT
Platform: UNKNOWN
